minestrone/__init__.py
minestrone/element/__init__.py
minestrone/element/prettifier.py
minestrone-0.9.0.dist-info/METADATA
minestrone-0.9.0.dist-info/WHEEL
minestrone-0.9.0.dist-info/licenses/LICENSE
minestrone-0.9.0.dist-info/RECORD
